pytidycensus/__init__.py
pytidycensus/acs.py
pytidycensus/api.py
pytidycensus/decennial.py
pytidycensus/estimates.py
pytidycensus/flows.py
pytidycensus/geography.py
pytidycensus/mapping.py
pytidycensus/time_series.py
pytidycensus/utils.py
pytidycensus/variables.py
pytidycensus/data/__init__.py
pytidycensus/data/acs_5_example_api.csv
pytidycensus/data/mig-flow-recode.csv
pytidycensus/data/national_county.txt
pytidycensus/llm_interface/__init__.py
pytidycensus/llm_interface/assistant.py
pytidycensus/llm_interface/cli.py
pytidycensus/llm_interface/conversation.py
pytidycensus/llm_interface/knowledge_base.py
pytidycensus/llm_interface/providers.py
pytidycensus-1.2.3.dist-info/licenses/LICENSE
pytidycensus-1.2.3.dist-info/METADATA
pytidycensus-1.2.3.dist-info/WHEEL
pytidycensus-1.2.3.dist-info/top_level.txt
pytidycensus-1.2.3.dist-info/RECORD
