Metadata-Version: 2.4
Name: pytidycensus
Version: 1.2.3
Summary: Python interface to US Census Bureau APIs with LLM, pandas and GeoPandas support
Author: Michael Mann mmann1123@gwu.edu
License: MIT
Project-URL: Homepage, https://github.com/mmann1123/pytidycensus
Project-URL: Documentation, https://mmann1123.github.io/pytidycensus
Project-URL: Repository, https://github.com/mmann1123/pytidycensus
Project-URL: Bug Reports, https://github.com/mmann1123/pytidycensus/issues
Classifier: Development Status :: 3 - Alpha
Classifier: Intended Audience :: Developers
Classifier: Intended Audience :: Science/Research
Classifier: License :: OSI Approved :: MIT License
Classifier: Operating System :: OS Independent
Classifier: Programming Language :: Python :: 3
Classifier: Programming Language :: Python :: 3.9
Classifier: Programming Language :: Python :: 3.10
Classifier: Programming Language :: Python :: 3.11
Classifier: Programming Language :: Python :: 3.12
Classifier: Programming Language :: Python :: 3.13
Classifier: Programming Language :: Python :: 3.14
Classifier: Topic :: Scientific/Engineering :: GIS
Classifier: Topic :: Software Development :: Libraries :: Python Modules
Requires-Python: >=3.9
License-File: LICENSE
Requires-Dist: pandas>=1.2.0; python_version < "3.13"
Requires-Dist: pandas>=2.0.0; python_version >= "3.13"
Requires-Dist: requests>=2.25.0
Requires-Dist: geopandas>=0.10.0
Requires-Dist: shapely>=1.8.0
Requires-Dist: pyproj>=3.0.0
Requires-Dist: us>=2.0.0
Requires-Dist: tqdm>=4.60.0
Requires-Dist: appdirs>=1.4.0
Requires-Dist: certifi>=2025.8.3
Requires-Dist: numpy>=1.21.0; python_version < "3.13"
Requires-Dist: numpy>=2.0.0; python_version >= "3.13"
Requires-Dist: pyyaml>=6.0.0
Requires-Dist: matplotlib>=3.5.0
Requires-Dist: pygris>=0.2.0
Requires-Dist: tobler>=0.12.1
Provides-Extra: dev
Requires-Dist: pytest>=6.0; extra == "dev"
Requires-Dist: pytest-cov>=2.12; extra == "dev"
Requires-Dist: pytest-mock>=3.6; extra == "dev"
Requires-Dist: pytest-asyncio>=0.20.0; extra == "dev"
Requires-Dist: black>=21.0; extra == "dev"
Requires-Dist: isort>=5.9; extra == "dev"
Requires-Dist: flake8>=3.9; extra == "dev"
Requires-Dist: mypy>=0.910; extra == "dev"
Requires-Dist: toml>=0.10.2; extra == "dev"
Requires-Dist: pre-commit; extra == "dev"
Requires-Dist: autopep8; extra == "dev"
Requires-Dist: autoflake; extra == "dev"
Requires-Dist: docformatter; extra == "dev"
Provides-Extra: docs
Requires-Dist: sphinx>=4.0; extra == "docs"
Requires-Dist: sphinx-rtd-theme>=1.0; extra == "docs"
Requires-Dist: myst-parser>=0.15; extra == "docs"
Requires-Dist: sphinx-autodoc-typehints>=1.12; extra == "docs"
Requires-Dist: nbsphinx>=0.8; extra == "docs"
Requires-Dist: jupyter>=1.0; extra == "docs"
Requires-Dist: ipython>=7.0; extra == "docs"
Requires-Dist: myst-nb>=1.3.0; extra == "docs"
Requires-Dist: tomli>=2.2.1; extra == "docs"
Requires-Dist: seaborn>=0.11.0; extra == "docs"
Requires-Dist: sphinxcontrib-googleanalytics>=0.5; extra == "docs"
Requires-Dist: sphinx-sitemap>=2.8.0; extra == "docs"
Provides-Extra: llm
Requires-Dist: openai>=1.0.0; extra == "llm"
Requires-Dist: ollama>=0.6.0; extra == "llm"
Requires-Dist: asyncio>=4.0.0; extra == "llm"
Requires-Dist: pytest-asyncio>=0.20.0; extra == "llm"
Provides-Extra: map
Requires-Dist: folium>=0.20.0; extra == "map"
Requires-Dist: contextily>=1.6.2; extra == "map"
Requires-Dist: branca>=0.8.2; extra == "map"
Requires-Dist: pyarrow>=19.0.0; extra == "map"
Requires-Dist: lonboard>=0.11.0; extra == "map"
Requires-Dist: palettable>=3.3.1; extra == "map"
Provides-Extra: time
Requires-Dist: tobler>=0.12.1; extra == "time"
Provides-Extra: all
Requires-Dist: pandas>=1.2.0; python_version < "3.13" and extra == "all"
Requires-Dist: pandas>=2.0.0; python_version >= "3.13" and extra == "all"
Requires-Dist: requests>=2.25.0; extra == "all"
Requires-Dist: geopandas>=0.10.0; extra == "all"
Requires-Dist: shapely>=1.8.0; extra == "all"
Requires-Dist: pyproj>=3.0.0; extra == "all"
Requires-Dist: us>=2.0.0; extra == "all"
Requires-Dist: tqdm>=4.60.0; extra == "all"
Requires-Dist: appdirs>=1.4.0; extra == "all"
Requires-Dist: certifi>=2025.8.3; extra == "all"
Requires-Dist: numpy>=1.21.0; python_version < "3.13" and extra == "all"
Requires-Dist: numpy>=2.0.0; python_version >= "3.13" and extra == "all"
Requires-Dist: pyyaml>=6.0.0; extra == "all"
Requires-Dist: matplotlib>=3.5.0; extra == "all"
Requires-Dist: pygris>=0.2.0; extra == "all"
Requires-Dist: pytest>=6.0; extra == "all"
Requires-Dist: pytest-cov>=2.12; extra == "all"
Requires-Dist: pytest-mock>=3.6; extra == "all"
Requires-Dist: pytest-asyncio>=0.20.0; extra == "all"
Requires-Dist: black>=21.0; extra == "all"
Requires-Dist: isort>=5.9; extra == "all"
Requires-Dist: flake8>=3.9; extra == "all"
Requires-Dist: mypy>=0.910; extra == "all"
Requires-Dist: toml>=0.10.2; extra == "all"
Requires-Dist: pre-commit; extra == "all"
Requires-Dist: autopep8; extra == "all"
Requires-Dist: autoflake; extra == "all"
Requires-Dist: docformatter; extra == "all"
Requires-Dist: sphinx>=4.0; extra == "all"
Requires-Dist: sphinx-rtd-theme>=1.0; extra == "all"
Requires-Dist: myst-parser>=0.15; extra == "all"
Requires-Dist: sphinx-autodoc-typehints>=1.12; extra == "all"
Requires-Dist: nbsphinx>=0.8; extra == "all"
Requires-Dist: jupyter>=1.0; extra == "all"
Requires-Dist: ipython>=7.0; extra == "all"
Requires-Dist: myst-nb>=1.3.0; extra == "all"
Requires-Dist: tomli>=2.2.1; extra == "all"
Requires-Dist: seaborn>=0.11.0; extra == "all"
Requires-Dist: sphinxcontrib-googleanalytics>=0.5; extra == "all"
Requires-Dist: sphinx-sitemap>=2.8.0; extra == "all"
Requires-Dist: openai>=1.0.0; extra == "all"
Requires-Dist: ollama>=0.6.0; extra == "all"
Requires-Dist: asyncio>=4.0.0; extra == "all"
Requires-Dist: tobler>=0.12.1; extra == "all"
Requires-Dist: folium>=0.20.0; extra == "all"
Requires-Dist: contextily>=1.6.2; extra == "all"
Requires-Dist: branca>=0.8.2; extra == "all"
Requires-Dist: pyarrow>=19.0.0; extra == "all"
Requires-Dist: lonboard>=0.11.0; extra == "all"
Requires-Dist: palettable>=3.3.1; extra == "all"
Dynamic: license-file
